EchoReaper/__init__.py
EchoReaper/connections.py
EchoReaper/get_proxies.py
EchoReaper/reaper.py
EchoReaper-1.0.2.dist-info/LICENSE
EchoReaper-1.0.2.dist-info/METADATA
EchoReaper-1.0.2.dist-info/WHEEL
EchoReaper-1.0.2.dist-info/top_level.txt
EchoReaper-1.0.2.dist-info/RECORD
