Metadata-Version: 2.1
Name: EchoReaper
Version: 1.0.2
Summary: A small library for scraping websites with or without proxy
Home-page: https://github.com/ad3002/EchoReaper
Author: Aleksey Komissarov
Author-email: ad3002@gmail.com
License: BSD
Classifier: Development Status :: 4 - Beta
Classifier: Environment :: Console
Classifier: Intended Audience :: Science/Research
Classifier: License :: OSI Approved :: BSD License
Classifier: Operating System :: OS Independent
Classifier: Programming Language :: Python
Classifier: Topic :: Scientific/Engineering :: Information Analysis
Requires-Python: >=3.6
License-File: LICENSE
Requires-Dist: seleniumbase ==4.21.1
Requires-Dist: webdriver-manager ==4.0.1
